commute_agci/__init__.py
commute_agci/commute_agci.py
commute_agci-0.6.6.dist-info/METADATA
commute_agci-0.6.6.dist-info/WHEEL
commute_agci-0.6.6.dist-info/top_level.txt
commute_agci-0.6.6.dist-info/RECORD
