Metadata-Version: 2.1
Name: commute_agci
Version: 0.6.6
Summary: commute_agci is a Python package for analyzing commute data.
Home-page: https://github.com/Ryomo0797/AudioAlchemist.git
Download-URL: https://github.com/Ryomo0797/AudioAlchemist.git
Author: Udai kishimoto
Author-email: s2222012@stu.musashino-u.ac.jp
Maintainer: Udai kishimoto
Maintainer-email: s2222012@stu.musashino-u.ac.jp
License: MIT
Keywords: commute_agci commute analysis data visualization
Classifier: License :: OSI Approved :: MIT License
Classifier: Programming Language :: Python :: 3.6
Requires-Dist: numpy
Requires-Dist: pandas
Requires-Dist: matplotlib
Requires-Dist: scipy
